MANIFEST.in
README.rst
fit.py
setup.py
python_fit.egg-info/PKG-INFO
python_fit.egg-info/SOURCES.txt
python_fit.egg-info/dependency_links.txt
python_fit.egg-info/top_level.txt