Metadata-Version: 1.1
Name: python-fit
Version: 1.0.0
Summary: A python module using scipy's orthogonal distance regression that makes fitting data easy.
Home-page: https://github.com/vgm64/python-fit
Author: Michael Woods
Author-email: physicsmichael@gmail.com
License: MIT
Keywords: fitting curve
Platform: UNKNOWN
Classifier: Development Status :: 5 - Production/Stable
Classifier: Topic :: Scientific/Engineering
Classifier: Topic :: Utilities
Classifier: Operating System :: OS Independent
Classifier: Intended Audience :: Science/Research
Classifier: Programming Language :: Python
Classifier: License :: OSI Approved :: MIT License
